unv/__init__.py
unv/utils/__init__.py
unv/utils/collections.py
unv/utils/files.py
unv/utils/os.py
unv/utils/tasks.py
unv.utils-0.4.1.dist-info/LICENSE
unv.utils-0.4.1.dist-info/METADATA
unv.utils-0.4.1.dist-info/WHEEL
unv.utils-0.4.1.dist-info/top_level.txt
unv.utils-0.4.1.dist-info/zip-safe
unv.utils-0.4.1.dist-info/RECORD
